{
  "product_id": "d8e913e6-24e9-41ee-a610-2f89ee1f2e69",
  "model": "CHANEL CC Chain Belt Gold Metal and Leather Circa 1990",
  "brand": "Chanel",
  "product_url": "https://www.1stdibs.com/fashion/accessories/belts/chanel-cc-chain-belt-gold-metal-leather-circa-1990/id-v_28349312/",
  "category": "1990s Belts",
  "seller_location": "SAINT-OUEN-SUR-SEINE, FR",
  "thumbnail_url": "https://a.1stdibscdn.com/chanel-cc-chain-belt-gold-metal-and-leather-circa-1990-for-sale-picture-2/v_44632/v_283493121768299053233/IMG_5717_master.jpg?width=240",
  "full_description": "\u00c9l\u00e9gante ceinture CHANEL CC Cha\u00eene entrelac\u00e9e, r\u00e9alis\u00e9e en m\u00e9tal dor\u00e9 et cuir de haute qualit\u00e9, symbole du style iconique de la Maison CHANEL \u00e0 la fin des ann\u00e9es 1980 et d\u00e9but des ann\u00e9es 1990. Ce mod\u00e8le incarne \u00e0 la fois raffinement et audace, apportant une touche luxueuse et unique \u00e0 toute tenue.\n\nLa ceinture pr\u00e9sente un design entrelac\u00e9 distinctif, avec le c\u00e9l\u00e8bre motif CC, refl\u00e9tant l\u2019\u00e9l\u00e9gance intemporelle et le savoir-faire exceptionnel de CHANEL. Elle peut se porter \u00e0 la taille ou sur les hanches, ajoutant structure et sophistication \u00e0 vos looks.\n\nEn tr\u00e8s bon \u00e9tat, cette ceinture est livr\u00e9e avec sa bo\u00eete d\u2019origine. Sa longueur de 70 cm la rend pratique et adaptable \u00e0 diff\u00e9rentes silhouettes.",
  "price": 1352.67,
  "main_images": [
    {
      "url": "https://scraping-framework-s3-public.s3.us-east-1.amazonaws.com/image_cache/dolce_gabbana/20260120_174706/d832b153693be3cd18d48a952484c49a.jpg",
      "format": "image/jpeg",
      "metadata": {
        "description": "CHANEL CC Chain Belt Gold Metal and Leather Circa 1990 For Sale",
        "upload_date": "2026-01-13T05:17:54.000-05:00",
        "original_url": "https://a.1stdibscdn.com/chanel-cc-chain-belt-gold-metal-and-leather-circa-1990-for-sale/v_44632/v_283493121768298970091/v_28349312_1768298971057_bg_processed.jpg?width=768"
      }
    },
    {
      "url": "https://scraping-framework-s3-public.s3.us-east-1.amazonaws.com/image_cache/dolce_gabbana/20260120_174654/a37be982a87dde16a61fdbcdec4ae9fd.jpg",
      "format": "image/jpeg",
      "metadata": {
        "description": "\u00c9l\u00e9gante ceinture CHANEL CC Cha\u00eene entrelac\u00e9e, r\u00e9alis\u00e9e en m\u00e9tal dor\u00e9 et cuir de haute qualit\u00e9, symbole du style iconique de la Maison CHANEL \u00e0 la fin des ann\u00e9es 1980 et d\u00e9but des ann\u00e9es 1990. Ce mod\u00e8le incarne \u00e0 la fois raffinement et audace,",
        "upload_date": "2026-01-13T05:17:54.000-05:00",
        "original_url": "https://a.1stdibscdn.com/chanel-cc-chain-belt-gold-metal-and-leather-circa-1990-for-sale-picture-2/v_44632/v_283493121768299053233/IMG_5717_master.jpg?width=768"
      }
    },
    {
      "url": "https://scraping-framework-s3-public.s3.us-east-1.amazonaws.com/image_cache/dolce_gabbana/20260120_174656/bf28594d690d7e3a4009aa3e9f1af7c8.jpg",
      "format": "image/jpeg",
      "metadata": {
        "description": "CHANEL CC Chain Belt Gold Metal and Leather Circa 1990 In Excellent Condition For Sale In SAINT-OUEN-SUR-SEINE, FR",
        "upload_date": "2026-01-13T05:17:54.000-05:00",
        "original_url": "https://a.1stdibscdn.com/chanel-cc-chain-belt-gold-metal-and-leather-circa-1990-for-sale-picture-3/v_44632/v_283493121768309968559/2026_01_12_11_33_41_master.jpg?width=768"
      }
    },
    {
      "url": "https://scraping-framework-s3-public.s3.us-east-1.amazonaws.com/image_cache/dolce_gabbana/20260120_174656/aab191673da042ce9b09d89be1307a6e.jpg",
      "format": "image/jpeg",
      "metadata": {
        "description": "Women's or Men's CHANEL CC Chain Belt Gold Metal and Leather Circa 1990 For Sale",
        "upload_date": "2026-01-13T05:17:54.000-05:00",
        "original_url": "https://a.1stdibscdn.com/chanel-cc-chain-belt-gold-metal-and-leather-circa-1990-for-sale-picture-3/v_44632/v_283493121768299053233/IMG_5720_master.jpg?width=768"
      }
    },
    {
      "url": "https://scraping-framework-s3-public.s3.us-east-1.amazonaws.com/image_cache/dolce_gabbana/20260120_174655/202121a66ec7035b3246fdf4efd6b2f0.jpg",
      "format": "image/jpeg",
      "metadata": {
        "description": "CHANEL CC Chain Belt Gold Metal and Leather Circa 1990 For Sale 1",
        "upload_date": "2026-01-13T05:17:54.000-05:00",
        "original_url": "https://a.1stdibscdn.com/chanel-cc-chain-belt-gold-metal-and-leather-circa-1990-for-sale-picture-4/v_44632/v_283493121768299053208/IMG_5721_master.jpg?width=768"
      }
    },
    {
      "url": "https://scraping-framework-s3-public.s3.us-east-1.amazonaws.com/image_cache/dolce_gabbana/20260120_174656/1bfdef2caf7001941a121ff965bc92cb.jpg",
      "format": "image/jpeg",
      "metadata": {
        "description": "CHANEL CC Chain Belt Gold Metal and Leather Circa 1990 For Sale 2",
        "upload_date": "2026-01-13T05:17:54.000-05:00",
        "original_url": "https://a.1stdibscdn.com/chanel-cc-chain-belt-gold-metal-and-leather-circa-1990-for-sale-picture-5/v_44632/v_283493121768299053233/IMG_5724_master.jpg?width=768"
      }
    },
    {
      "url": "https://scraping-framework-s3-public.s3.us-east-1.amazonaws.com/image_cache/dolce_gabbana/20260120_174655/8f3277e87f278db336e49a2caad65510.jpg",
      "format": "image/jpeg",
      "metadata": {
        "description": "CHANEL CC Chain Belt Gold Metal and Leather Circa 1990 For Sale 3",
        "upload_date": "2026-01-13T05:17:54.000-05:00",
        "original_url": "https://a.1stdibscdn.com/chanel-cc-chain-belt-gold-metal-and-leather-circa-1990-for-sale-picture-6/v_44632/v_283493121768299053496/IMG_5768_master.jpg?width=768"
      }
    },
    {
      "url": "https://scraping-framework-s3-public.s3.us-east-1.amazonaws.com/image_cache/dolce_gabbana/20260120_174659/ce174e64479c9962a5b95e922275fc67.jpg",
      "format": "image/jpeg",
      "metadata": {
        "description": "CHANEL CC Chain Belt Gold Metal and Leather Circa 1990 For Sale 4",
        "upload_date": "2026-01-13T05:17:54.000-05:00",
        "original_url": "https://a.1stdibscdn.com/chanel-cc-chain-belt-gold-metal-and-leather-circa-1990-for-sale-picture-7/v_44632/v_283493121768299053371/IMG_5774_master.jpg?width=768"
      }
    },
    {
      "url": "https://scraping-framework-s3-public.s3.us-east-1.amazonaws.com/image_cache/dolce_gabbana/20260120_174655/cf39328764585ad77df83c366094b713.jpg",
      "format": "image/jpeg",
      "metadata": {
        "description": "CHANEL CC Chain Belt Gold Metal and Leather Circa 1990 For Sale 5",
        "upload_date": "2026-01-13T05:17:54.000-05:00",
        "original_url": "https://a.1stdibscdn.com/chanel-cc-chain-belt-gold-metal-and-leather-circa-1990-for-sale-picture-8/v_44632/v_283493121768299054504/IMG_5777_master.jpg?width=768"
      }
    },
    {
      "url": "https://scraping-framework-s3-public.s3.us-east-1.amazonaws.com/image_cache/dolce_gabbana/20260120_174655/778acee75e5d8e9f1ccdbf3655d711f7.jpg",
      "format": "image/jpeg",
      "metadata": {
        "description": "CHANEL CC Chain Belt Gold Metal and Leather Circa 1990 For Sale 6",
        "upload_date": "2026-01-13T05:17:54.000-05:00",
        "original_url": "https://a.1stdibscdn.com/chanel-cc-chain-belt-gold-metal-and-leather-circa-1990-for-sale-picture-9/v_44632/v_283493121768299054491/IMG_5781_master.jpg?width=768"
      }
    }
  ],
  "metadata": {
    "condition_display": "Excellent",
    "reference_number": "Seller: A122502",
    "period": "1990-1999",
    "length": "25.6 in (65 cm)",
    "designer": "Chanel",
    "dimensions": "Length: 25.6 in (65 cm)",
    "condition": "Excellent",
    "seller_location": "SAINT-OUEN-SUR-SEINE, FR",
    "category": "1990s Belts",
    "production_date": "1990-1999",
    "item_condition": "Used Condition",
    "availability": "In Stock",
    "all_prices": {
      "AUD": 2021.43,
      "CHF": 1080.31,
      "MXN": 23826.88,
      "EUR": 1140.0,
      "GBP": 1009.84,
      "DKK": 8688.08,
      "CAD": 1879.27,
      "USD": 1352.67,
      "SEK": 12451.43,
      "NOK": 13620.18
    }
  },
  "session_id": "1110cc0d-6d07-4a7d-9e65-a7f07e328a83",
  "brand_id": "chanel",
  "function_id": "macro_luxury_authentication"
}